{
    "os": "Windows-10-10.0.22000-SP0",
    "python": "3.9.13",
    "heartbeatAt": "2022-08-07T13:03:25.285987",
    "startedAt": "2022-08-07T13:03:24.718232",
    "docker": null,
    "gpu": "Tesla V100-PCIE-16GB",
    "gpu_count": 1,
    "cpu_count": 6,
    "cuda": null,
    "args": [],
    "state": "running",
    "program": "C:\\Users\\psiml8\\Desktop\\Projekat\\graph-transformer-psiml\\main.py",
    "codePath": "main.py",
    "git": {
        "remote": "https://github.com/njmarko/graph-transformer-psiml.git",
        "commit": "310449c1fffb1a51d1a3282c05486676ca81dfe5"
    },
    "email": "marko.njegomir@uns.ac.rs",
    "root": "C:/Users/psiml8/Desktop/Projekat/graph-transformer-psiml",
    "host": "lab00000S",
    "username": "psiml8",
    "executable": "C:\\Users\\psiml8\\AppData\\Local\\Programs\\Python\\Python39\\python.exe"
}
